{
  "generated_at_et": "2026-04-05 04:06 ET",
  "market_data_as_of": "2026-04-02 16:00 ET (Close)",
  "status": "ok",
  "error": null,
  "items": [
    {
      "ticker": "NVDA",
      "ai_score": 75,
      "ai_state": "강세",
      "ai_action": "보유 유지",
      "ai_note": "NVIDIA는 Marvell과 파트너십을 맺고 AI 생태계를 확장하고 있습니다. 최근 로봇 공학 및 자율 주행 기술 협력도 발표하며 AI 분야에서의 리더십을 강화하고 있습니다. 현재 추세는 긍정적이며, 보유 중이라면 계속 보유하는 것을 추천합니다.",
      "close": 177.4,
      "change_pct": 0.9388335704125117,
      "score": 35,
      "state": "약함",
      "action": "회피 / 비중 축소",
      "cross_highlights": [],
      "volume_ratio_20d": 0.0,
      "signals": {
        "short_cross": "none",
        "mid_cross": "none"
      }
    },
    {
      "ticker": "TSLA",
      "ai_score": 20,
      "ai_state": "약세",
      "ai_action": "관망",
      "ai_note": "Tesla의 1분기 인도량이 예상치를 하회했으며, Cybertruck 판매량도 감소했습니다. CEO 머스크의 새로운 보상 패키지 승인 여부도 주시해야 합니다. 현재로서는 관망하며 추가적인 하락세를 지켜보는 것이 좋겠습니다.",
      "close": 360.5587,
      "change_pct": -5.429709184121068,
      "score": 14,
      "state": "회피",
      "action": "회피 / 비중 축소",
      "cross_highlights": [],
      "volume_ratio_20d": 0.0,
      "signals": {
        "short_cross": "none",
        "mid_cross": "none"
      }
    },
    {
      "ticker": "META",
      "ai_score": 25,
      "ai_state": "약세",
      "ai_action": "관망",
      "ai_note": "Meta는 아동 성 착취 관련 소송에서 패소하여 3억 7,500만 달러의 민사 손해배상 판결을 받았습니다. 또한, AI 챗봇 관련 안전 문제로 논란이 있습니다. 당분간은 관망하며 법적 이슈와 회사 대응을 지켜보는 것이 좋겠습니다.",
      "close": 574.45,
      "change_pct": -0.8252301555388586,
      "score": 16,
      "state": "회피",
      "action": "회피 / 비중 축소",
      "cross_highlights": [],
      "volume_ratio_20d": 0.0,
      "signals": {
        "short_cross": "none",
        "mid_cross": "none"
      }
    },
    {
      "ticker": "AMD",
      "ai_score": 60,
      "ai_state": "중립",
      "ai_action": "보유 유지",
      "ai_note": "AMD는 AI 및 데이터센터 기술에 집중하며 삼성, NAVER 클라우드 등과 협력하고 있습니다. 다만, 데이터센터 사업부의 성장 전망이 기대에 미치지 못한다는 소식도 있습니다. 현재로서는 보유를 유지하되, AI 관련 신규 사업 성과를 주시하는 것이 좋겠습니다.",
      "close": 217.68,
      "change_pct": 3.5535859604917786,
      "score": 40,
      "state": "약함",
      "action": "회피 / 비중 축소",
      "cross_highlights": [],
      "volume_ratio_20d": 0.0,
      "signals": {
        "short_cross": "none",
        "mid_cross": "none"
      }
    },
    {
      "ticker": "TEM",
      "ai_score": 55,
      "ai_state": "중립",
      "ai_action": "보유 유지",
      "ai_note": "Tempus AI는 AI 기반 의료 솔루션 개발에 집중하고 있으며, Merck와 협력하여 정밀 의학을 가속화하고 있습니다. ALERT 임상 시험 결과도 긍정적입니다. 현재 추세는 중립적이며, 보유 중이라면 계속 보유하는 것을 추천합니다.",
      "close": 47.39,
      "change_pct": 0.7654714651228245,
      "score": 16,
      "state": "회피",
      "action": "회피 / 비중 축소",
      "cross_highlights": [],
      "volume_ratio_20d": 0.0,
      "signals": {
        "short_cross": "none",
        "mid_cross": "none"
      }
    },
    {
      "ticker": "SOXX",
      "ai_score": 45,
      "ai_state": "약보합",
      "ai_action": "관망",
      "ai_note": "반도체 ETF인 SOXX는 최근 AI 관련 뉴스로 주목받고 있으나, 지정학적 리스크와 공급망 이슈도 존재합니다. 현재로서는 관망하며 반도체 섹터 전반의 흐름을 지켜보는 것이 좋겠습니다.",
      "close": 339.85,
      "change_pct": 0.38695321734900645,
      "score": 36,
      "state": "약함",
      "action": "회피 / 비중 축소",
      "cross_highlights": [],
      "volume_ratio_20d": 0.0,
      "signals": {
        "short_cross": "none",
        "mid_cross": "none"
      }
    },
    {
      "ticker": "SERV",
      "ai_score": 30,
      "ai_state": "약세",
      "ai_action": "비중 축소",
      "ai_note": "Serve Robotics는 로봇 배달 사업을 확장하고 있으나, 최근 주가 목표 하향 조정 소식이 있었습니다. 또한, 내부자 매도 물량이 관찰됩니다. 현재로서는 비중 축소를 고려하는 것이 좋겠습니다.",
      "close": 8.45,
      "change_pct": 0.4756260798292278,
      "score": 11,
      "state": "회피",
      "action": "회피 / 비중 축소",
      "cross_highlights": [],
      "volume_ratio_20d": 0.0,
      "signals": {
        "short_cross": "none",
        "mid_cross": "none"
      }
    },
    {
      "ticker": "KORU",
      "ai_score": 10,
      "ai_state": "매우 약세",
      "ai_action": "매도",
      "ai_note": "KORU Medical Systems는 4분기 실적은 좋았으나, CEO 교체 소식이 있었습니다. 최근 중기 데드크로스가 발생했으며, 시장 대비 약한 흐름을 보이고 있습니다. 현재로서는 매도를 고려하는 것이 좋겠습니다.",
      "close": 280.04,
      "change_pct": -8.47169309026594,
      "score": 6,
      "state": "회피",
      "action": "회피 / 비중 축소",
      "cross_highlights": [
        "KORU 최근 중기 데드크로스: 20일선이 50일선 아래로 내려갔습니다. 거래량 0.0x (거래량 약함) / RSI 46 (중립)"
      ],
      "volume_ratio_20d": 0.0,
      "signals": {
        "short_cross": "none",
        "mid_cross": "bear"
      }
    }
  ]
}