{
  "generated_at_et": "2026-05-07 19:46 ET",
  "market_data_as_of": "2026-05-07 15:50 ET (5분봉)",
  "status": "ok",
  "error": null,
  "items": [
    {
      "ticker": "NVDA",
      "ai_score": 78,
      "ai_state": "매수 고려",
      "ai_action": "선별 매수",
      "ai_note": "최근 5일선이 20일선을 상향 돌파하는 단기 골든크로스 발생, 거래량은 약하나 RSI 58로 상승 추세 유지 중. 시장 대비 강한 흐름을 보이며 50일선 위에 있어 긍정적. 보유 중이라면 단기 지지선 이탈 시 분할 매도 고려.",
      "close": 211.8699951171875,
      "change_pct": 1.9438932062450398,
      "score": 75,
      "state": "양호",
      "action": "선별 매수",
      "cross_highlights": [
        "NVDA 최근 단기 골든크로스: 5일선이 20일선을 위로 돌파했습니다. 거래량 0.0x (거래량 약함) / RSI 58 (상방 우세)"
      ],
      "volume_ratio_20d": 0.012872186315004672,
      "signals": {
        "short_cross": "bull",
        "mid_cross": "none"
      }
    },
    {
      "ticker": "TSLA",
      "ai_score": 65,
      "ai_state": "관망",
      "ai_action": "보류 / 관찰",
      "ai_note": "시장 대비 강한 흐름을 보이고 50일선 및 20일선 위에 있으나, 명확한 매수 신호는 부족. 현재 구간에서는 추가적인 방향성 확인 후 진입 고려.",
      "close": 406.0350036621094,
      "change_pct": 1.8320649247622667,
      "score": 63,
      "state": "애매",
      "action": "보류 / 관찰",
      "cross_highlights": [],
      "volume_ratio_20d": 0.009296493492955714,
      "signals": {
        "short_cross": "none",
        "mid_cross": "none"
      }
    },
    {
      "ticker": "META",
      "ai_score": 35,
      "ai_state": "매도 고려",
      "ai_action": "보류 / 관찰",
      "ai_note": "최근 5일선이 20일선을 하향 돌파하는 단기 데드크로스 발생, RSI 26으로 과매도 구간 진입. 20일선 아래에 있고 시장 대비 약한 흐름. 보유 중이라면 20일선 재돌파 여부 확인 후 손절 고려.",
      "close": 617.1900024414062,
      "change_pct": 0.7032367713510013,
      "score": 29,
      "state": "회피",
      "action": "보류 / 관찰",
      "cross_highlights": [
        "META 최근 단기 데드크로스: 5일선이 20일선 아래로 내려갔습니다. 거래량 0.0x (거래량 약함) / RSI 26 (과매도 구간)",
        "META 최근 중기 골든크로스: 20일선이 50일선을 위로 돌파했습니다. 거래량 0.0x (거래량 약함) / RSI 26 (과매도 구간)"
      ],
      "volume_ratio_20d": 0.008434054332171358,
      "signals": {
        "short_cross": "bear",
        "mid_cross": "bull"
      }
    },
    {
      "ticker": "AMD",
      "ai_score": 82,
      "ai_state": "매수 고려",
      "ai_action": "선별 매수",
      "ai_note": "시장 대비 강한 흐름을 보이며 50일선 및 20일선 위에 위치. RSI 76으로 과열 구간 진입 가능성 있으나 상승 추세는 견고함. 보유 중이라면 단기 급등에 따른 조정 가능성 염두.",
      "close": 408.7701110839844,
      "change_pct": -2.994827386923682,
      "score": 79,
      "state": "양호",
      "action": "선별 매수",
      "cross_highlights": [],
      "volume_ratio_20d": 0.01381399033641803,
      "signals": {
        "short_cross": "none",
        "mid_cross": "none"
      }
    },
    {
      "ticker": "TEM",
      "ai_score": 60,
      "ai_state": "관망",
      "ai_action": "보류 / 관찰",
      "ai_note": "20일선이 50일선을 상향 돌파하는 중기 골든크로스 발생했으나, 거래량은 약하고 RSI 37로 하방 압력 존재. 시장 대비 강한 흐름과 약한 흐름이 혼재되어 관망 필요.",
      "close": 49.45000076293945,
      "change_pct": -7.570092031888875,
      "score": 57,
      "state": "애매",
      "action": "보류 / 관찰",
      "cross_highlights": [
        "TEM 최근 중기 골든크로스: 20일선이 50일선을 위로 돌파했습니다. 거래량 0.1x (거래량 약함) / RSI 37 (하방 우세)"
      ],
      "volume_ratio_20d": 0.06024086162138372,
      "signals": {
        "short_cross": "none",
        "mid_cross": "bull"
      }
    },
    {
      "ticker": "SOXX",
      "ai_score": 77,
      "ai_state": "매수 고려",
      "ai_action": "선별 매수",
      "ai_note": "시장 대비 강한 흐름을 보이며 50일선 및 20일선 위에 위치. RSI 74로 상승 추세 강함. 반도체 섹터 전반의 흐름을 따라갈 가능성 높음. 보유 중이라면 추세 이탈 시 분할 매도 고려.",
      "close": 493.80999755859375,
      "change_pct": -2.5765970928254056,
      "score": 74,
      "state": "양호",
      "action": "선별 매수",
      "cross_highlights": [],
      "volume_ratio_20d": 0.05520489419470878,
      "signals": {
        "short_cross": "none",
        "mid_cross": "none"
      }
    },
    {
      "ticker": "SERV",
      "ai_score": 58,
      "ai_state": "관망",
      "ai_action": "보류 / 관찰",
      "ai_note": "20일선이 50일선을 상향 돌파하는 중기 골든크로스 발생했으나, 5일선이 20일선을 하향 돌파하는 단기 데드크로스도 동시에 발생. RSI 45로 중립 구간. 혼조세이므로 추가적인 방향성 확인 필요.",
      "close": 9.130000114440918,
      "change_pct": -4.697284058965345,
      "score": 56,
      "state": "애매",
      "action": "보류 / 관찰",
      "cross_highlights": [
        "SERV 최근 단기 데드크로스: 5일선이 20일선 아래로 내려갔습니다. 거래량 0.0x (거래량 약함) / RSI 45 (중립)",
        "SERV 최근 중기 골든크로스: 20일선이 50일선을 위로 돌파했습니다. 거래량 0.0x (거래량 약함) / RSI 45 (중립)"
      ],
      "volume_ratio_20d": 0.02488621815630406,
      "signals": {
        "short_cross": "bear",
        "mid_cross": "bull"
      }
    },
    {
      "ticker": "KORU",
      "ai_score": 68,
      "ai_state": "관망",
      "ai_action": "보류 / 관찰",
      "ai_note": "20일선이 50일선을 상향 돌파하는 중기 골든크로스 발생, RSI 69로 상승 우세. 다만 최근 급등으로 인한 부담감 존재. 보유 중이라면 단기 급등에 따른 조정 가능성 염두.",
      "close": 770.530029296875,
      "change_pct": -8.160902348405841,
      "score": 64,
      "state": "애매",
      "action": "보류 / 관찰",
      "cross_highlights": [
        "KORU 최근 중기 골든크로스: 20일선이 50일선을 위로 돌파했습니다. 거래량 0.0x (거래량 약함) / RSI 69 (상방 우세)"
      ],
      "volume_ratio_20d": 0.006767772268242645,
      "signals": {
        "short_cross": "none",
        "mid_cross": "bull"
      }
    }
  ]
}